gawsoft/api_client/__init__.py
gawsoft/api_client/exception.py
gawsoft/api_client/request.py
gawsoft/api_client/response.py
gawsoft/api_client/version.py
gawsoft_api_client-0.1.12.dist-info/licenses/LICENSE
gawsoft_api_client-0.1.12.dist-info/METADATA
gawsoft_api_client-0.1.12.dist-info/WHEEL
gawsoft_api_client-0.1.12.dist-info/top_level.txt
gawsoft_api_client-0.1.12.dist-info/RECORD
