Metadata-Version: 2.4
Name: gawsoft_api_client
Version: 0.1.12
Summary: Rest Api Client
Author-email: "Gawsoft.com" <contact@gawsoft.com>
License-Expression: MIT
Project-URL: Homepage, https://gawsoft.com
Project-URL: Repository, https://github.com/gawsoftpl/rest-api-client-framework-python
Classifier: Programming Language :: Python :: 3
Classifier: Operating System :: OS Independent
Requires-Python: >=3.8
License-File: LICENSE
Dynamic: license-file
